abbrev.py
abbrev-1.2.1.dist-info/LICENSE
abbrev-1.2.1.dist-info/METADATA
abbrev-1.2.1.dist-info/WHEEL
abbrev-1.2.1.dist-info/RECORD
