Metadata-Version: 2.1
Name: abbrev
Version: 1.2.1
Summary: 🐜 Expand abbreviations 🐜
Home-page: https://github.com/rec/abbrev
License: MIT
Author: Tom Ritchford
Author-email: tom@swirly.com
Requires-Python: >=3.8
Classifier: License :: OSI Approved :: MIT License
Classifier: Programming Language :: Python :: 3
Classifier: Programming Language :: Python :: 3.8
Classifier: Programming Language :: Python :: 3.9
Classifier: Programming Language :: Python :: 3.10
Classifier: Programming Language :: Python :: 3.11
Classifier: Programming Language :: Python :: 3.12
Requires-Dist: xmod
Project-URL: Documentation, https://rec.github.io/abbrev
Project-URL: Repository, https://github.com/rec/abbrev
